diffpatch.py
diffpatch-1.1.0.dist-info/METADATA
diffpatch-1.1.0.dist-info/WHEEL
diffpatch-1.1.0.dist-info/top_level.txt
diffpatch-1.1.0.dist-info/RECORD
