Metadata-Version: 2.1
Name: diffpatch
Version: 1.1.0
Summary: A library to make and apply patches
Home-page: https://gist.github.com/noporpoise/16e731849eb1231e86d78f9dfeca3abc
Author: Isaac Turner
Author-email: UNKNOWN
License: UNKNOWN
Platform: UNKNOWN
